setup.cfg
setup.py
nx_spatial/__init__.py
nx_spatial.egg-info/PKG-INFO
nx_spatial.egg-info/SOURCES.txt
nx_spatial.egg-info/dependency_links.txt
nx_spatial.egg-info/entry_points.txt
nx_spatial.egg-info/not-zip-safe
nx_spatial.egg-info/top_level.txt
nx_spatial/algorithms/__init__.py
nx_spatial/algorithms/attr_find.py
nx_spatial/algorithms/flow_errors.py
nx_spatial/algorithms/setdirection.py
nx_spatial/algorithms/trace.py
nx_spatial/readwrite/__init__.py
nx_spatial/readwrite/nx_esrifc.py
nx_spatial/readwrite/nx_shp.py