Metadata-Version: 1.0
Name: nx-spatial
Version: 0.3dev
Summary: Additional GIS focused functions for networkx graphs.
Home-page: http://bitbucket.org/gallipoli/nx_spatial
Author: Ben Reilly
Author-email: gallipoli@gmail.com
License: MPL
Keywords: spatial,gis,topology,networkx
Platform: UNKNOWN
Classifier: Topic :: Scientific/Engineering :: GIS
